autolevels/__init__.py
autolevels/autolevels.py
autolevels/export.py
autolevels/inference.py
autolevels/data/__init__.py
autolevels/data/dt_template_v5.xmp
autolevels-1.3.4.dist-info/entry_points.txt
autolevels-1.3.4.dist-info/licenses/LICENSE
autolevels-1.3.4.dist-info/WHEEL
autolevels-1.3.4.dist-info/METADATA
autolevels-1.3.4.dist-info/RECORD
