Metadata-Version: 2.4
Name: autolevels
Version: 1.3.4
Summary: A tool for automatic photo enhancement using curve corrections.
Author-email: Marius Wanko <marius.wanko@gmail.com>
Requires-Python: >=3.9
Classifier: Programming Language :: Python :: 3.9
Classifier: License :: OSI Approved :: GNU General Public License v3 (GPLv3)
Classifier: Operating System :: OS Independent
Classifier: Topic :: Multimedia :: Graphics
License-File: LICENSE
Requires-Dist: numpy
Requires-Dist: pillow
Requires-Dist: piexif>=1.1.1,<2.0.0
Requires-Dist: opencv-python
Requires-Dist: h5py
Requires-Dist: onnxruntime
Requires-Dist: pytest ; extra == "dev"
Requires-Dist: flake8 ; extra == "dev"
Project-URL: Changelog, https://github.com/yellowdolphin/autolevels/blob/master/CHANGELOG.md
Project-URL: Homepage, https://github.com/yellowdolphin/autolevels
Project-URL: Issues, https://github.com/yellowdolphin/autolevels/issues
Provides-Extra: dev
